qvsed/__init__.py
qvsed/config_default.py
qvsed/qvsed.py
qvsed/qvsed.ui
qvsed/qvsed_dialog.ui
qvsed-1.6.1.dist-info/LICENSE.txt
qvsed-1.6.1.dist-info/METADATA
qvsed-1.6.1.dist-info/WHEEL
qvsed-1.6.1.dist-info/entry_points.txt
qvsed-1.6.1.dist-info/top_level.txt
qvsed-1.6.1.dist-info/RECORD
