Metadata-Version: 2.1
Name: qvsed
Version: 1.6.1
Summary: Qt-Based Volatile Small Editor
Home-page: https://github.com/That1M8Head/QVSED/
Author: Arsalan Kazmi
License: GPL-3.0-or-later
License-File: LICENSE.txt
Requires-Dist: PyQt5
